celerybeatmongo/__init__.py
celerybeatmongo/schedulers.py
celerybeatmongo/schemas.py
celerybeatmongo-0.1.2.dist-info/DESCRIPTION.rst
celerybeatmongo-0.1.2.dist-info/METADATA
celerybeatmongo-0.1.2.dist-info/RECORD
celerybeatmongo-0.1.2.dist-info/WHEEL
celerybeatmongo-0.1.2.dist-info/metadata.json
celerybeatmongo-0.1.2.dist-info/top_level.txt
